.editorconfig
.gitignore
.gitlab-ci.yml
README.rst
publish.settings.sh
publish.sh
pyproject.toml
tsconfig.json
.idea/modules.xml
.idea/peek-core-docdb.iml
.idea/inspectionProfiles/Project_Default.xml
.idea/inspectionProfiles/profiles_settings.xml
peek_core_docdb/PlatformDependencyTest.py
peek_core_docdb/__init__.py
peek_core_docdb/plugin_package.json
peek_core_docdb.egg-info/PKG-INFO
peek_core_docdb.egg-info/SOURCES.txt
peek_core_docdb.egg-info/dependency_links.txt
peek_core_docdb.egg-info/requires.txt
peek_core_docdb.egg-info/top_level.txt
peek_core_docdb/_private/PluginNames.py
peek_core_docdb/_private/__init__.py
peek_core_docdb/_private/alembic.ini
peek_core_docdb/_private/admin-app/docDb.module.ts
peek_core_docdb/_private/admin-app/components/docdb-page/docdb-page.component.html
peek_core_docdb/_private/admin-app/components/docdb-page/docdb-page.component.scss
peek_core_docdb/_private/admin-app/components/docdb-page/docdb-page.component.ts
peek_core_docdb/_private/admin-app/components/edit-object-type/edit-object-type.component.html
peek_core_docdb/_private/admin-app/components/edit-object-type/edit-object-type.component.scss
peek_core_docdb/_private/admin-app/components/edit-object-type/edit-object-type.component.ts
peek_core_docdb/_private/admin-app/components/edit-property/edit-property.component.html
peek_core_docdb/_private/admin-app/components/edit-property/edit-property.component.scss
peek_core_docdb/_private/admin-app/components/edit-property/edit-property.component.ts
peek_core_docdb/_private/admin-app/components/edit-setting/edit-setting.component.html
peek_core_docdb/_private/admin-app/components/edit-setting/edit-setting.component.scss
peek_core_docdb/_private/admin-app/components/edit-setting/edit-setting.component.ts
peek_core_docdb/_private/admin-app/components/status/status.component.html
peek_core_docdb/_private/admin-app/components/status/status.component.scss
peek_core_docdb/_private/admin-app/components/status/status.component.ts
peek_core_docdb/_private/admin-app/components/view-document/view-document.component.html
peek_core_docdb/_private/admin-app/components/view-document/view-document.component.scss
