Metadata-Version: 2.4
Name: peek-core-docdb
Version: 5.0.4
Summary: Peek Core Plugin DocDB - an online/offline storage for simple JSON documents
Author-email: Synerty <contact@synerty.com>
Project-URL: Homepage, https://github.com/Synerty/peek-core-docdb
Keywords: Peek,Python,Platform,synerty
Requires-Dist: peek-plugin-base==5.0.4
